app_config.py
gui.py
history.py
logging_config.py
organizer.py
rules.py
scheduler.py
sfo_file_organizer-1.0.1.dist-info/METADATA
sfo_file_organizer-1.0.1.dist-info/WHEEL
sfo_file_organizer-1.0.1.dist-info/entry_points.txt
sfo_file_organizer-1.0.1.dist-info/top_level.txt
sfo_file_organizer-1.0.1.dist-info/RECORD
