Metadata-Version: 2.4
Name: sfo-file-organizer
Version: 1.0.1
Summary: A Python utility that automatically organizes files into categorized folders based on file types, with rule-based classification and real-time monitoring.
Author: pjames-tech
License: MIT
Project-URL: Homepage, https://github.com/pjames-tech/sfo-file-organizer
Project-URL: Repository, https://github.com/pjames-tech/sfo-file-organizer
Project-URL: Issues, https://github.com/pjames-tech/sfo-file-organizer/issues
Keywords: file-organizer,automation,file-management,desktop-app
Classifier: Development Status :: 5 - Production/Stable
Classifier: Environment :: Console
Classifier: Environment :: MacOS X
Classifier: Environment :: Win32 (MS Windows)
Classifier: Intended Audience :: End Users/Desktop
Classifier: License :: OSI Approved :: MIT License
Classifier: Operating System :: OS Independent
Classifier: Programming Language :: Python :: 3
Classifier: Programming Language :: Python :: 3.8
Classifier: Programming Language :: Python :: 3.9
Classifier: Programming Language :: Python :: 3.10
Classifier: Programming Language :: Python :: 3.11
Classifier: Programming Language :: Python :: 3.12
Classifier: Topic :: Desktop Environment :: File Managers
Classifier: Topic :: System :: Filesystems
Classifier: Topic :: Utilities
Requires-Python: >=3.8
Requires-Dist: watchdog>=3.0.0
Provides-Extra: dev
Requires-Dist: pytest>=7.0.0; extra == "dev"
Requires-Dist: pyinstaller>=6.0.0; extra == "dev"
